[
  {
    "id": "KC17-内七彩-001",
    "name": "内七彩",
    "rating": "",
    "comment": ""
  },
  {
    "id": "KC17-多巴胺-001",
    "name": "多巴胺",
    "rating": "",
    "comment": ""
  },
  {
    "id": "KC17-大炫彩-001",
    "name": "大炫彩",
    "rating": "",
    "comment": ""
  },
  {
    "id": "KC17-小炫彩-001",
    "name": "小炫彩",
    "rating": "",
    "comment": ""
  },
  {
    "id": "KC17-小香芋-001",
    "name": "小香芋",
    "rating": "",
    "comment": ""
  },
  {
    "id": "KC17-威龙-001",
    "name": "威龙",
    "rating": "",
    "comment": ""
  }
]