[
  {
    "id": "M4A1-低调黑-001",
    "folderCode": "UQ低调黑",
    "normalizedCode": "UQ",
    "weapon": "M4A1",
    "serial": "001",
    "imageA": "../M4A1/UQ低调黑/M4A1-低调黑-001_A.png",
    "imageB": "../M4A1/UQ低调黑/M4A1-低调黑-001_B.png",
    "imageC": "../M4A1/UQ低调黑/M4A1-低调黑-001_C.png",
    "imageD": "../M4A1/UQ低调黑/M4A1-低调黑-001_D.png",
    "status": "ready",
    "template": "低调黑",
    "qualityLabel": "优品",
    "materialLabel": "其他",
    "colorLabel": "NA"
  },
  {
    "id": "M4A1-初音未来-001",
    "folderCode": "UQ初音未来",
    "normalizedCode": "UQ",
    "weapon": "M4A1",
    "serial": "001",
    "imageA": "../M4A1/UQ初音未来/M4A1-初音未来-001_A.png",
    "imageB": "../M4A1/UQ初音未来/M4A1-初音未来-001_B.png",
    "imageC": "../M4A1/UQ初音未来/M4A1-初音未来-001_C.png",
    "imageD": "../M4A1/UQ初音未来/M4A1-初音未来-001_D.png",
    "status": "ready",
    "template": "初音未来",
    "qualityLabel": "优品",
    "materialLabel": "其他",
    "colorLabel": "NA"
  },
  {
    "id": "M4A1-曼巴-001",
    "folderCode": "UQ曼巴",
    "normalizedCode": "UQ",
    "weapon": "M4A1",
    "serial": "001",
    "imageA": "../M4A1/UQ曼巴/M4A1-曼巴-001_A.png",
    "imageB": "../M4A1/UQ曼巴/M4A1-曼巴-001_B.png",
    "imageC": "../M4A1/UQ曼巴/M4A1-曼巴-001_C.png",
    "imageD": "../M4A1/UQ曼巴/M4A1-曼巴-001_D.png",
    "status": "ready",
    "template": "曼巴",
    "qualityLabel": "优品",
    "materialLabel": "其他",
    "colorLabel": "NA"
  },
  {
    "id": "M4A1-牙膏白-001",
    "folderCode": "UQ牙膏白",
    "normalizedCode": "UQ",
    "weapon": "M4A1",
    "serial": "001",
    "imageA": "../M4A1/UQ牙膏白/M4A1-牙膏白-001_A.png",
    "imageB": "../M4A1/UQ牙膏白/M4A1-牙膏白-001_B.png",
    "imageC": "../M4A1/UQ牙膏白/M4A1-牙膏白-001_C.png",
    "imageD": "../M4A1/UQ牙膏白/M4A1-牙膏白-001_D.png",
    "status": "ready",
    "template": "牙膏白",
    "qualityLabel": "优品",
    "materialLabel": "其他",
    "colorLabel": "NA"
  }
]